domain93/__main__.py
domain93/data/eng.traineddata
domain93/data/tesseract-linux
domain93/data/windows/ambiguous_words.1.html
domain93/data/windows/classifier_tester.1.html
domain93/data/windows/cntraining.1.html
domain93/data/windows/combine_lang_model.1.html
domain93/data/windows/combine_tessdata.1.html
domain93/data/windows/dawg2wordlist.1.html
domain93/data/windows/doc/AUTHORS
domain93/data/windows/doc/LICENSE
domain93/data/windows/doc/README.md
domain93/data/windows/libLerc.dll
domain93/data/windows/libarchive-13.dll
domain93/data/windows/libb2-1.dll
domain93/data/windows/libbrotlicommon.dll
domain93/data/windows/libbrotlidec.dll
domain93/data/windows/libbz2-1.dll
domain93/data/windows/libcairo-2.dll
domain93/data/windows/libcrypto-3-x64.dll
domain93/data/windows/libcurl-4.dll
domain93/data/windows/libdatrie-1.dll
domain93/data/windows/libdeflate.dll
domain93/data/windows/libexpat-1.dll
domain93/data/windows/libffi-8.dll
domain93/data/windows/libfontconfig-1.dll
domain93/data/windows/libfreetype-6.dll
domain93/data/windows/libfribidi-0.dll
domain93/data/windows/libgcc_s_seh-1.dll
domain93/data/windows/libgif-7.dll
domain93/data/windows/libgio-2.0-0.dll
domain93/data/windows/libglib-2.0-0.dll
domain93/data/windows/libgmodule-2.0-0.dll
domain93/data/windows/libgobject-2.0-0.dll
domain93/data/windows/libgraphite2.dll
domain93/data/windows/libharfbuzz-0.dll
domain93/data/windows/libiconv-2.dll
domain93/data/windows/libicudt75.dll
domain93/data/windows/libicuin75.dll
domain93/data/windows/libicuuc75.dll
domain93/data/windows/libidn2-0.dll
domain93/data/windows/libintl-8.dll
domain93/data/windows/libjbig-0.dll
domain93/data/windows/libjpeg-8.dll
domain93/data/windows/libleptonica-6.dll
domain93/data/windows/liblz4.dll
domain93/data/windows/liblzma-5.dll
domain93/data/windows/libopenjp2-7.dll
domain93/data/windows/libpango-1.0-0.dll
domain93/data/windows/libpangocairo-1.0-0.dll
domain93/data/windows/libpangoft2-1.0-0.dll
domain93/data/windows/libpangowin32-1.0-0.dll
domain93-1.2.1.dist-info/METADATA
domain93-1.2.1.dist-info/WHEEL
domain93-1.2.1.dist-info/entry_points.txt
domain93-1.2.1.dist-info/licenses/LICENSE
domain93-1.2.1.dist-info/RECORD
