Metadata-Version: 2.4
Name: domain93
Version: 1.2.1
Summary: A totally rad GUI tool to automate freedns link creation
License-File: LICENSE
Author: Cbass92
Author-email: contact@cbass92.org
Requires-Python: >=3.9
Classifier: Programming Language :: Python :: 3
Classifier: Programming Language :: Python :: 3.9
Classifier: Programming Language :: Python :: 3.10
Classifier: Programming Language :: Python :: 3.11
Classifier: Programming Language :: Python :: 3.12
Classifier: Programming Language :: Python :: 3.13
Classifier: Programming Language :: Python :: 3.14
Requires-Dist: art (>=6.4,<7.0)
Requires-Dist: freedns-client (>=0.1.3,<0.2.0)
Requires-Dist: lolpython (>=2.2.0,<3.0.0)
Requires-Dist: pillow (>=10.0.0)
Requires-Dist: pysocks (>=1.7.1,<2.0.0)
Requires-Dist: pytesseract (>=0.3.13,<0.4.0)
Requires-Dist: requests (>=2.32.3,<3.0.0)
Requires-Dist: stem (>=1.8.2,<2.0.0)
Requires-Dist: ttkbootstrap (>=1.10.1,<2.0.0)
Project-URL: Repository, https://github.com/LexLeethorMain/domain93
